flexmeasures_client/__init__.py
flexmeasures_client/client.py
flexmeasures_client/constants.py
flexmeasures_client/exceptions.py
flexmeasures_client/response_handling.py
flexmeasures_client/s2/__init__.py
flexmeasures_client/s2/cem.py
flexmeasures_client/s2/const.py
flexmeasures_client/s2/utils.py
flexmeasures_client/s2/wrapper.py
flexmeasures_client/s2/control_types/__init__.py
flexmeasures_client/s2/control_types/translations.py
flexmeasures_client/s2/control_types/FRBC/__init__.py
flexmeasures_client/s2/control_types/FRBC/frbc_simple.py
flexmeasures_client/s2/control_types/FRBC/frbc_tunes.py
flexmeasures_client/s2/control_types/FRBC/utils.py
flexmeasures_client/s2/script/demo_setup.py
flexmeasures_client/s2/script/websockets_client.py
flexmeasures_client/s2/script/websockets_server.py
flexmeasures_client-0.8.0.dist-info/licenses/LICENSE.txt
flexmeasures_client-0.8.0.dist-info/METADATA
flexmeasures_client-0.8.0.dist-info/WHEEL
flexmeasures_client-0.8.0.dist-info/top_level.txt
flexmeasures_client-0.8.0.dist-info/RECORD
