Metadata-Version: 2.4
Name: flexmeasures-client
Version: 0.8.0
Summary: Async client to connect to the FlexMeasures API
Home-page: https://github.com/FlexMeasures/flexmeasures-client
Author: Flexmeasures
Author-email: info@seita.nl
License: APACHE
Platform: any
Classifier: Development Status :: 4 - Beta
Classifier: Programming Language :: Python
License-File: LICENSE.txt
Requires-Dist: importlib-metadata; python_version < "3.8"
Requires-Dist: aiohttp
Requires-Dist: pandas>=2.1.4
Requires-Dist: async_timeout
Requires-Dist: packaging
Provides-Extra: s2
Requires-Dist: requests; extra == "s2"
Requires-Dist: s2-python; extra == "s2"
Requires-Dist: semver; extra == "s2"
Provides-Extra: testing
Requires-Dist: setuptools; extra == "testing"
Requires-Dist: pytest; extra == "testing"
Requires-Dist: pytest-cov; extra == "testing"
Requires-Dist: pytest-asyncio; extra == "testing"
Requires-Dist: pytest-mock; extra == "testing"
Requires-Dist: aioresponses>=0.7.8; extra == "testing"
Dynamic: license-file
